deepdespeckling/__init__.py
deepdespeckling/denoiser.py
deepdespeckling/despeckling.py
deepdespeckling/model.py
deepdespeckling/test_deepdespeckling.py
deepdespeckling/merlin/__init__.py
deepdespeckling/merlin/merlin_denoiser.py
deepdespeckling/merlin/inference/__init__.py
deepdespeckling/merlin/inference/merlin_denoiser.py
deepdespeckling/merlin/saved_model/spotlight.pth
deepdespeckling/merlin/saved_model/stripmap.pth
deepdespeckling/merlin/saved_models/.DS_Store
deepdespeckling/merlin/saved_models/sentinel_tops.pth
deepdespeckling/merlin/saved_models/spotlight.pth
deepdespeckling/merlin/saved_models/stripmap.pth
deepdespeckling/merlin/training/Dataset.py
deepdespeckling/merlin/training/GenerateDataset.py
deepdespeckling/merlin/training/__init__.py
deepdespeckling/merlin/training/model.py
deepdespeckling/merlin/training/train.py
deepdespeckling/merlin/training/saved_model/model.pth
deepdespeckling/sar2sar/__init__.py
deepdespeckling/sar2sar/sar2sar_denoiser.py
deepdespeckling/sar2sar/saved_model/.DS_Store
deepdespeckling/sar2sar/saved_model/sar2sar.pth
deepdespeckling/utils/__init__.py
deepdespeckling/utils/constants.py
deepdespeckling/utils/load_cosar.py
deepdespeckling/utils/utils.py
deepdespeckling-0.8.dist-info/LICENSE
deepdespeckling-0.8.dist-info/METADATA
deepdespeckling-0.8.dist-info/WHEEL
deepdespeckling-0.8.dist-info/entry_points.txt
deepdespeckling-0.8.dist-info/top_level.txt
deepdespeckling-0.8.dist-info/RECORD
