Metadata-Version: 2.1
Name: deepdespeckling
Version: 0.8
Summary: Python Boilerplate contains all the boilerplate you need to create a Python package.
Home-page: https://github.com/hi-paris/deepdespeckling
Author: Emanuele Dalsasso, Hadrien Mariaccia, Youcef Kemiche, Pierre Blanchard
Author-email: engineer@hi-paris.fr
License: MIT license
Keywords: deepdespeckling
Platform: UNKNOWN
Classifier: Development Status :: 2 - Pre-Alpha
Classifier: Intended Audience :: Developers
Classifier: License :: OSI Approved :: MIT License
Classifier: Environment :: Console
Classifier: Operating System :: OS Independent
Classifier: Operating System :: POSIX :: Linux
Classifier: Operating System :: MacOS
Classifier: Operating System :: POSIX
Classifier: Operating System :: Microsoft :: Windows
Classifier: Natural Language :: English
Classifier: Programming Language :: Python :: 3
Classifier: Programming Language :: Python :: 3.6
Classifier: Programming Language :: Python :: 3.7
Classifier: Programming Language :: Python :: 3.8
Classifier: Programming Language :: Python :: 3.9
Requires-Python: >=3.6
License-File: LICENSE
Requires-Dist: numpy
Requires-Dist: Pillow
Requires-Dist: scipy
Requires-Dist: torch
Requires-Dist: opencv-python
Requires-Dist: tqdm
